<?xml version="1.0" encoding="utf-8" ?><dwsync><file name="RoHai.htm" server="coryskarate.com/coryskarate.com/" local="3629336235" remote="1876656208083108752" /><file name="AdvancedII.htm" server="coryskarate.com/coryskarate.com/" local="3629336235" remote="1876656208083108752" /><file name="AdvancedIV.htm" server="coryskarate.com/coryskarate.com/" local="3629336235" remote="1876656208083108752" /><file name="DonGuan.htm" server="coryskarate.com/coryskarate.com/" local="3629336235" remote="1876656208083108752" /><file name="RoHaiII.htm" server="coryskarate.com/coryskarate.com/" local="3629336235" remote="1876656208083108752" /><file name="RoHaiII_new.htm" server="coryskarate.com/coryskarate.com/" local="3629336235" remote="1876656208083108752" /><file name="Tekki-Shodan.htm" server="coryskarate.com/coryskarate.com/" local="3629336235" remote="1876656208083108752" /><file name="AdvancedIII.htm" server="coryskarate.com/coryskarate.com/" local="3629336235" remote="391973768627700564" /></dwsync>